LICENCE
gradient_aware_harmonisation-0.4.0.dist-info/METADATA
gradient_aware_harmonisation-0.4.0.dist-info/WHEEL
gradient_aware_harmonisation-0.4.0.dist-info/entry_points.txt
gradient_aware_harmonisation-0.4.0.dist-info/licenses/LICENCE
gradient_aware_harmonisation/__init__.py
gradient_aware_harmonisation/exceptions.py
gradient_aware_harmonisation/helpers.py
gradient_aware_harmonisation/py.typed
gradient_aware_harmonisation/spline.py
gradient_aware_harmonisation/utils.py
gradient_aware_harmonisation-0.4.0.dist-info/RECORD
