Metadata-Version: 2.1
Name: gradient-aware-harmonisation
Version: 0.4.0
Summary: gradient aware harmonisation of timeseries
Author-Email: Florence Bockting <florence.bockting@climate-resource.com>
License: 3-Clause BSD License
Classifier: Development Status :: 3 - Alpha
Classifier: Intended Audience :: Science/Research
Classifier: License :: OSI Approved :: BSD License
Classifier: Natural Language :: English
Classifier: Operating System :: OS Independent
Classifier: Programming Language :: Python
Classifier: Programming Language :: Python :: 3
Classifier: Programming Language :: Python :: 3 :: Only
Classifier: Programming Language :: Python :: 3.9
Classifier: Programming Language :: Python :: 3.10
Classifier: Programming Language :: Python :: 3.11
Classifier: Programming Language :: Python :: 3.12
Classifier: Programming Language :: Python :: 3.13
Classifier: Typing :: Typed
Project-URL: Homepage, https://gradient-aware-harmonisation.readthedocs.io
Project-URL: Documentation, https://gradient-aware-harmonisation.readthedocs.io
Project-URL: Changelog, https://gradient-aware-harmonisation.readthedocs.io/en/stable/changelog
Project-URL: Repository, https://github.com/climate-resource/gradient-aware-harmonisation
Project-URL: Issues, https://github.com/climate-resource/gradient-aware-harmonisation/issues
Requires-Python: >=3.9
Requires-Dist: attrs>=24.3.0
Requires-Dist: numpy>=1.25.0
Requires-Dist: pandas>=2.2.3
Provides-Extra: plots
Requires-Dist: matplotlib>=3.7.1; extra == "plots"
Provides-Extra: scipy
Requires-Dist: scipy>=1.13.1; extra == "scipy"
Provides-Extra: full
Requires-Dist: gradient-aware-harmonisation[plots]; extra == "full"
Requires-Dist: gradient-aware-harmonisation[scipy]; extra == "full"
Provides-Extra: locked
Requires-Dist: attrs==24.3.0; python_version >= "3.11" and extra == "locked"
Requires-Dist: numpy==2.2.4; python_version >= "3.11" and extra == "locked"
Requires-Dist: pandas==2.2.3; python_version >= "3.11" and extra == "locked"
Requires-Dist: python-dateutil==2.9.0.post0; python_version >= "3.11" and extra == "locked"
Requires-Dist: pytz==2025.1; python_version >= "3.11" and extra == "locked"
Requires-Dist: six==1.17.0; python_version >= "3.11" and extra == "locked"
Requires-Dist: tzdata==2025.1; python_version >= "3.11" and extra == "locked"
Provides-Extra: plots-locked
Requires-Dist: contourpy==1.3.1; python_version >= "3.11" and extra == "plots-locked"
Requires-Dist: cycler==0.12.1; python_version >= "3.11" and extra == "plots-locked"
Requires-Dist: fonttools==4.56.0; python_version >= "3.11" and extra == "plots-locked"
Requires-Dist: kiwisolver==1.4.8; python_version >= "3.11" and extra == "plots-locked"
Requires-Dist: matplotlib==3.10.1; python_version >= "3.11" and extra == "plots-locked"
Requires-Dist: numpy==2.2.4; python_version >= "3.11" and extra == "plots-locked"
Requires-Dist: packaging==24.2; python_version >= "3.11" and extra == "plots-locked"
Requires-Dist: pillow==11.1.0; python_version >= "3.11" and extra == "plots-locked"
Requires-Dist: pyparsing==3.2.1; python_version >= "3.11" and extra == "plots-locked"
Requires-Dist: python-dateutil==2.9.0.post0; python_version >= "3.11" and extra == "plots-locked"
Requires-Dist: six==1.17.0; python_version >= "3.11" and extra == "plots-locked"
Provides-Extra: scipy-locked
Requires-Dist: numpy==2.2.4; python_version >= "3.11" and extra == "scipy-locked"
Requires-Dist: scipy==1.15.2; python_version >= "3.11" and extra == "scipy-locked"
Provides-Extra: full-locked
Requires-Dist: contourpy==1.3.1; python_version >= "3.11" and extra == "full-locked"
Requires-Dist: cycler==0.12.1; python_version >= "3.11" and extra == "full-locked"
Requires-Dist: fonttools==4.56.0; python_version >= "3.11" and extra == "full-locked"
Requires-Dist: kiwisolver==1.4.8; python_version >= "3.11" and extra == "full-locked"
Requires-Dist: matplotlib==3.10.1; python_version >= "3.11" and extra == "full-locked"
Requires-Dist: numpy==2.2.4; python_version >= "3.11" and extra == "full-locked"
Requires-Dist: packaging==24.2; python_version >= "3.11" and extra == "full-locked"
Requires-Dist: pillow==11.1.0; python_version >= "3.11" and extra == "full-locked"
Requires-Dist: pyparsing==3.2.1; python_version >= "3.11" and extra == "full-locked"
Requires-Dist: python-dateutil==2.9.0.post0; python_version >= "3.11" and extra == "full-locked"
Requires-Dist: scipy==1.15.2; python_version >= "3.11" and extra == "full-locked"
Requires-Dist: six==1.17.0; python_version >= "3.11" and extra == "full-locked"
